[{"name": "严一字", "school_id": 10, "college_id": 87, "phone": "13944744869", "email": "yiziyan@ybu.edu.cn", "job_title": "副教授", "abstracts": null, "directions": null, "education_experience": null, "work_experience": null, "patent": null, "project": null, "award": null, "social_job": null, "picture": "https://nxy.ybu.edu.cn/__local/1/FE/68/3CC56BB9F31822DA19F05D42C30_9C63F080_6413.jpg", "education": "研究生", "qualification": "博士", "job_information": 1, "responsibilities": null, "office_address": null}, {"name": "严春龙", "school_id": 10, "college_id": 87, "phone": "13944703211", "email": "yancl@ybu.edu.cn", "job_title": "讲师", "abstracts": null, "directions": null, "education_experience": null, "work_experience": null, "patent": null, "project": null, "award": null, "social_job": null, "picture": "https://nxy.ybu.edu.cn/__local/E/4F/B7/A00152026D1044C18B5D5B80A50_D28E8795_2EC3F.jpg", "education": "研究生", "qualification": "博士", "job_information": 1, "responsibilities": null, "office_address": null}, {"name": "于龙政", "school_id": 10, "college_id": 87, "phone": "13904432012", "email": "0000005727@ybu.edu.cn", "job_title": "副教授", "abstracts": null, "directions": null, "education_experience": null, "work_experience": null, "patent": null, "project": null, "award": null, "social_job": null, "picture": "https://nxy.ybu.edu.cn/__local/7/51/50/4F6D5BE17B865FD3DA3E077DD2A_912CDF70_6A11.jpg", "education": "研究生", "qualification": "博士", "job_information": 1, "responsibilities": null, "office_address": null}, {"name": "傅民杰", "school_id": 10, "college_id": 87, "phone": "13944760938", "email": "fuminjie@163.com", "job_title": "副教授", "abstracts": null, "directions": null, "education_experience": null, "work_experience": null, "patent": null, "project": null, "award": null, "social_job": null, "picture": "https://nxy.ybu.edu.cn/__local/1/05/46/DBE74F3C18FD6266C9695D33255_A867A63F_78B0.jpg", "education": "研究生", "qualification": "博士", "job_information": 1, "responsibilities": null, "office_address": null}, {"name": "全林虎", "school_id": 10, "college_id": 87, "phone": "18243301765", "email": "lhquan@ybu.edu.cn", "job_title": "教授", "abstracts": null, "directions": null, "education_experience": null, "work_experience": null, "patent": null, "project": null, "award": null, "social_job": null, "picture": "https://nxy.ybu.edu.cn/__local/7/5E/6F/4933021F243E6B22E97E869F558_9C15246D_7D2B.jpg", "education": "研究生", "qualification": "博士", "job_information": 1, "responsibilities": null, "office_address": null}, {"name": "全雪丽", "school_id": 10, "college_id": 87, "phone": "0433-2435590", "email": "qxl2000@aliyun.com", "job_title": "教授", "abstracts": null, "directions": null, "education_experience": null, "work_experience": null, "patent": null, "project": null, "award": null, "social_job": null, "picture": "https://nxy.ybu.edu.cn/__local/0/07/4F/B7536806A079D589330721988BF_4E4AE469_6798.jpg", "education": "研究生", "qualification": "博士", "job_information": 1, "responsibilities": null, "office_address": null}, {"name": "具红光", "school_id": 10, "college_id": 87, "phone": "0433-2435562", "email": "hgju@ybu.edu.cn", "job_title": "副教授", "abstracts": null, "directions": null, "education_experience": null, "work_experience": null, "patent": null, "project": null, "award": null, "social_job": null, "picture": "https://nxy.ybu.edu.cn/__local/E/75/3E/1CC645E9A0304F266046A2067A3_8AFCF30C_75CA.jpg", "education": "研究生", "qualification": "博士", "job_information": 1, "responsibilities": null, "office_address": null}, {"name": "冉丽萍", "school_id": 10, "college_id": 87, "phone": "13704432210", "email": "lpran@ybu.edu.cn", "job_title": "讲师", "abstracts": null, "directions": null, "education_experience": null, "work_experience": null, "patent": null, "project": null, "award": null, "social_job": null, "picture": "https://nxy.ybu.edu.cn/__local/7/7F/DB/BF6BD6D9EE648378B4521538C4A_337790A0_55DE.jpg", "education": "研究生", "qualification": "硕士", "job_information": 1, "responsibilities": null, "office_address": null}, {"name": "刘海峰", "school_id": 10, "college_id": 87, "phone": null, "email": "lhf@ybu.edu.cn", "job_title": "副教授", "abstracts": null, "directions": null, "education_experience": null, "work_experience": null, "patent": null, "project": null, "award": null, "social_job": null, "picture": "https://nxy.ybu.edu.cn/__local/0/F5/A8/BD3FA37DD04B9E9ED8102827947_5F48AD74_18E7.jpg", "education": "研究生", "qualification": "博士", "job_information": 1, "responsibilities": null, "office_address": null}, {"name": "刘继生", "school_id": 10, "college_id": 87, "phone": "13500911133", "email": "jsliu@ybu.edu.cn", "job_title": "教授", "abstracts": null, "directions": null, "education_experience": null, "work_experience": null, "patent": null, "project": null, "award": null, "social_job": null, "picture": "https://nxy.ybu.edu.cn/__local/7/72/99/ED40029D0E70BA507D545E9048E_56E93E4B_BF89A.jpg", "education": "本科", "qualification": "学士", "job_information": 1, "responsibilities": null, "office_address": null}, {"name": "刘迪", "school_id": 10, "college_id": 87, "phone": "13944386266", "email": "liudi@ybu.edu.cn", "job_title": "副教授", "abstracts": null, "directions": null, "education_experience": null, "work_experience": null, "patent": null, "project": null, "award": null, "social_job": null, "picture": "https://nxy.ybu.edu.cn/__local/9/3E/C7/6A6999A2418BC8E2F9021C75EDE_EA2D22E7_607A.jpg", "education": "研究生", "qualification": "博士", "job_information": 1, "responsibilities": null, "office_address": null}, {"name": "南力", "school_id": 10, "college_id": 87, "phone": "18104332507", "email": "nanli12@163.com", "job_title": "讲师", "abstracts": null, "directions": null, "education_experience": null, "work_experience": null, "patent": null, "project": null, "award": null, "social_job": null, "picture": "https://nxy.ybu.edu.cn/__local/3/ED/3D/E3455A03728AAF46B56A12F7A23_F0567F33_5E5C.jpg", "education": "研究生", "qualification": "博士", "job_information": 1, "responsibilities": null, "office_address": null}, {"name": "南桂仙", "school_id": 10, "college_id": 87, "phone": null, "email": "nanguixian@ybu.edu.cn", "job_title": "讲师", "abstracts": null, "directions": null, "education_experience": null, "work_experience": null, "patent": null, "project": null, "award": null, "social_job": null, "picture": "https://nxy.ybu.edu.cn/__local/3/F5/56/BB0DCBD8036ED15F8290F965499_534BECAD_7510.jpg", "education": "研究生", "qualification": "博士", "job_information": 1, "responsibilities": null, "office_address": null}, {"name": "吴委林", "school_id": 10, "college_id": 87, "phone": "0433-2435569", "email": "wlwu@ybu.edu.cn", "job_title": "讲师", "abstracts": null, "directions": null, "education_experience": null, "work_experience": null, "patent": null, "project": null, "award": null, "social_job": null, "picture": "https://nxy.ybu.edu.cn/__local/5/2B/6B/20624821DF89C35F59A56402F0B_E4129665_66E2.jpg", "education": "研究生", "qualification": "博士", "job_information": 1, "responsibilities": null, "office_address": null}, {"name": "吴明根", "school_id": 10, "college_id": 87, "phone": "0433-2435566", "email": "5minggen@163.com", "job_title": "教授", "abstracts": null, "directions": null, "education_experience": null, "work_experience": null, "patent": null, "project": null, "award": null, "social_job": null, "picture": "https://nxy.ybu.edu.cn/__local/C/C1/BE/87BB5773E1898DD73CC9AA2E647_9438668E_1BB57.png", "education": "研究生", "qualification": "博士", "job_information": 1, "responsibilities": null, "office_address": null}, {"name": "吴松权", "school_id": 10, "college_id": 87, "phone": "18943705331", "email": "arswsq@ybu.edu.cn", "job_title": "教授", "abstracts": null, "directions": null, "education_experience": null, "work_experience": null, "patent": null, "project": null, "award": null, "social_job": null, "picture": "https://nxy.ybu.edu.cn/__local/0/E0/41/2A94AAC6F3E870BB54845ABF78C_9CDFD8C7_3F85C.png", "education": "研究生", "qualification": "博士", "job_information": 1, "responsibilities": null, "office_address": null}, {"name": "吴玉德", "school_id": 10, "college_id": 87, "phone": "0433-2438202", "email": null, "job_title": "副教授", "abstracts": null, "directions": null, "education_experience": null, "work_experience": null, "patent": null, "project": null, "award": null, "social_job": null, "picture": "https://nxy.ybu.edu.cn/__local/1/B7/FD/497555F7962E91328DF138C8B04_6DE71CD4_DD7E.jpg", "education": "本科", "qualification": "学士", "job_information": 1, "responsibilities": null, "office_address": null}, {"name": "吴荣哲", "school_id": 10, "college_id": 87, "phone": "13689705192", "email": "wurzh@ybu.edu.cn", "job_title": "副教授", "abstracts": null, "directions": null, "education_experience": null, "work_experience": null, "patent": null, "project": null, "award": null, "social_job": null, "picture": "https://nxy.ybu.edu.cn/__local/2/6C/CD/97CB3C874C7AC57601D2BF76D14_35B809C1_2BC2.png", "education": "研究生", "qualification": "博士", "job_information": 1, "responsibilities": null, "office_address": null}, {"name": "周静雅", "school_id": 10, "college_id": 87, "phone": "15585561787", "email": "0000008750@ybu.edu.cn", "job_title": "讲师", "abstracts": null, "directions": null, "education_experience": null, "work_experience": null, "patent": null, "project": null, "award": null, "social_job": null, "picture": "https://nxy.ybu.edu.cn/__local/6/49/AC/791B859E51DDD1C28F1592C6BDF_618897A3_964A8.png", "education": "研究生", "qualification": "博士", "job_information": 1, "responsibilities": null, "office_address": null}, {"name": "夏广军", "school_id": 10, "college_id": 87, "phone": "13844705548", "email": "ybuac@ybu.edu.cn", "job_title": "教授", "abstracts": null, "directions": null, "education_experience": null, "work_experience": null, "patent": null, "project": null, "award": null, "social_job": null, "picture": "https://nxy.ybu.edu.cn/__local/3/C9/A5/EAAFCA9386BD7FE92ADB331C400_30AED0C9_621B.jpg", "education": "研究生", "qualification": "博士", "job_information": 1, "responsibilities": null, "office_address": null}, {"name": "姜君", "school_id": 10, "college_id": 87, "phone": null, "email": null, "job_title": "讲师", "abstracts": null, "directions": null, "education_experience": null, "work_experience": null, "patent": null, "project": null, "award": null, "social_job": null, "picture": "https://nxy.ybu.edu.cn/__local/B/47/92/8B19C0120E9F33F0DB0C7D2204A_63D1316D_2FCB.jpg", "education": "研究生", "qualification": "博士", "job_information": 1, "responsibilities": null, "office_address": null}, {"name": "姜君", "school_id": 10, "college_id": 87, "phone": "15834962332", "email": "jiangjun@ybu.edu.cn", "job_title": "副教授", "abstracts": null, "directions": null, "education_experience": null, "work_experience": null, "patent": null, "project": null, "award": null, "social_job": null, "picture": "https://nxy.ybu.edu.cn/__local/2/42/A0/9941274FE6FE2C402FFCB827EFE_33586489_1CDB.jpeg", "education": "研究生", "qualification": "博士", "job_information": 1, "responsibilities": null, "office_address": null}, {"name": "姜成哲", "school_id": 10, "college_id": 87, "phone": "0433-2435591", "email": "czjiang@ybu.edu.cn", "job_title": "教授", "abstracts": null, "directions": null, "education_experience": null, "work_experience": null, "patent": null, "project": null, "award": null, "social_job": null, "picture": "https://nxy.ybu.edu.cn/__local/9/E2/09/1D2A3781FDE68D3B561F9D4F769_7E5BED0A_2BB6.jpg", "education": "研究生", "qualification": "博士", "job_information": 1, "responsibilities": null, "office_address": null}, {"name": "姬文秀", "school_id": 10, "college_id": 87, "phone": "0433-2435586", "email": "jwxlyq@ybu.edu.cn", "job_title": "讲师", "abstracts": null, "directions": null, "education_experience": null, "work_experience": null, "patent": null, "project": null, "award": null, "social_job": null, "picture": "https://nxy.ybu.edu.cn/__local/8/2C/8E/A3E9C918A39AE4397A31C3B0C3B_059E8F47_5687.jpg", "education": "研究生", "qualification": "博士", "job_information": 1, "responsibilities": null, "office_address": null}, {"name": "娄安刚", "school_id": 10, "college_id": 87, "phone": "0433-2733279", "email": "aglou@ybu.edu.cn", "job_title": "讲师", "abstracts": null, "directions": null, "education_experience": null, "work_experience": null, "patent": null, "project": null, "award": null, "social_job": null, "picture": "https://nxy.ybu.edu.cn/__local/7/BF/44/5D06981FDE5B419CCBAC2F57233_F392A656_506C.jpg", "education": "研究生", "qualification": "博士", "job_information": 1, "responsibilities": null, "office_address": null}, {"name": "孔琳", "school_id": 10, "college_id": 87, "phone": "15143336676", "email": "konglin@ybu.edu.cn", "job_title": "实验师", "abstracts": null, "directions": null, "education_experience": null, "work_experience": null, "patent": null, "project": null, "award": null, "social_job": null, "picture": "https://nxy.ybu.edu.cn/__local/F/63/09/8779004C67840559173A76A8BEA_6D6F68D8_5D7F.jpg", "education": "研究生", "qualification": "博士", "job_information": 1, "responsibilities": null, "office_address": null}, {"name": "孙福亮", "school_id": 10, "college_id": 87, "phone": "13843350440", "email": "flsun@ybu.eud.cn", "job_title": "副教授", "abstracts": null, "directions": null, "education_experience": null, "work_experience": null, "patent": null, "project": null, "award": null, "social_job": null, "picture": "https://nxy.ybu.edu.cn/__local/B/0F/0F/990F5361F523A1D8D0D99B5AEF6_7AEE89F1_63313.png", "education": "研究生", "qualification": "博士", "job_information": 1, "responsibilities": null, "office_address": null}, {"name": "安松浩", "school_id": 10, "college_id": 87, "phone": "13844361509", "email": "ansonghao@ybu.edu.cn", "job_title": "讲师", "abstracts": null, "directions": null, "education_experience": null, "work_experience": null, "patent": null, "project": null, "award": null, "social_job": null, "picture": "https://nxy.ybu.edu.cn/__local/0/DF/7F/FBC57B7AA1224FE3DDEFDF91488_EAAA8A9B_654C5.jpg", "education": "研究生", "qualification": "博士", "job_information": 1, "responsibilities": null, "office_address": null}, {"name": "安金花", "school_id": 10, "college_id": 87, "phone": "0433-2435548", "email": "jinhuaan0303@163.com", "job_title": "高级实验师", "abstracts": null, "directions": null, "education_experience": null, "work_experience": null, "patent": null, "project": null, "award": null, "social_job": null, "picture": "https://nxy.ybu.edu.cn/__local/6/D5/83/DCE92724FFA3F97185E0F7AEF6E_E699B641_667B.jpg", "education": "研究生", "qualification": "硕士", "job_information": 1, "responsibilities": null, "office_address": null}, {"name": "宋建臣", "school_id": 10, "college_id": 87, "phone": "0433-2435539", "email": "jcsong@ybu.edu.cn", "job_title": "副教授", "abstracts": null, "directions": null, "education_experience": null, "work_experience": null, "patent": null, "project": null, "award": null, "social_job": null, "picture": "https://nxy.ybu.edu.cn/__local/A/B4/0F/974CB7A71A9954D4091D665959C_D716CB49_364F.jpg", "education": "本科", "qualification": "学士", "job_information": 1, "responsibilities": null, "office_address": null}, {"name": "宗成文", "school_id": 10, "college_id": 87, "phone": "0433-2435536", "email": "xgwang@ybu.edu.cn", "job_title": "副教授", "abstracts": null, "directions": null, "education_experience": null, "work_experience": null, "patent": null, "project": null, "award": null, "social_job": null, "picture": "https://nxy.ybu.edu.cn/__local/9/58/08/FEFE18A556D7B6CAC3468C3C53F_F6910467_3DD0.png", "education": "研究生", "qualification": "博士", "job_information": 1, "responsibilities": null, "office_address": null}, {"name": "尹振浩", "school_id": 10, "college_id": 87, "phone": "13043380770", "email": "yzh2015@ybu.edu.cn", "job_title": "讲师", "abstracts": null, "directions": null, "education_experience": null, "work_experience": null, "patent": null, "project": null, "award": null, "social_job": null, "picture": "https://nxy.ybu.edu.cn/__local/3/0D/D0/EFFF96DC7CDA8B196D36DB40604_8C5ABAC6_6A1A.png", "education": "研究生", "qualification": "博士", "job_information": 1, "responsibilities": null, "office_address": null}, {"name": "尹星福", "school_id": 10, "college_id": 87, "phone": null, "email": "yinxingfu@ybu.edu.cn", "job_title": "讲师", "abstracts": null, "directions": null, "education_experience": null, "work_experience": null, "patent": null, "project": null, "award": null, "social_job": null, "picture": "https://nxy.ybu.edu.cn/__local/D/64/F2/CA0C887B7A120C7DA7855F4D335_9373CCA3_24FE.jpg", "education": "研究生", "qualification": "博士", "job_information": 1, "responsibilities": null, "office_address": null}, {"name": "尹熙俊", "school_id": 10, "college_id": 87, "phone": "15944347933", "email": "Yinxijun@ybu.edu.cn", "job_title": "教授", "abstracts": null, "directions": null, "education_experience": null, "work_experience": null, "patent": null, "project": null, "award": null, "social_job": null, "picture": "https://nxy.ybu.edu.cn/__local/7/CB/46/6170DD83B071BA5BC54BC865C03_1963EE1F_78F9.jpg", "education": "研究生", "qualification": "博士", "job_information": 1, "responsibilities": null, "office_address": null}, {"name": "崔成都", "school_id": 10, "college_id": 87, "phone": "13943369112", "email": "cdcui@ybu.edu.cn", "job_title": "教授", "abstracts": null, "directions": null, "education_experience": null, "work_experience": null, "patent": null, "project": null, "award": null, "social_job": null, "picture": "https://nxy.ybu.edu.cn/__local/3/D9/39/BF66F4097AF1D583CE4BB3BFEE8_E8977795_AB649.jpg", "education": "研究生", "qualification": "博士", "job_information": 1, "responsibilities": null, "office_address": null}, {"name": "崔承弼", "school_id": 10, "college_id": 87, "phone": "0433-2436150", "email": "cuichengbi@ybu.edu.cn", "job_title": "教授", "abstracts": null, "directions": null, "education_experience": null, "work_experience": null, "patent": null, "project": null, "award": null, "social_job": null, "picture": "https://nxy.ybu.edu.cn/__local/8/FF/9C/CE2798B62A10115197083D4EA4C_61DD96BB_56BA.jpg", "education": "研究生", "qualification": "博士", "job_information": 1, "responsibilities": null, "office_address": null}, {"name": "崔明勋", "school_id": 10, "college_id": 87, "phone": "0433-2435611", "email": "1501967915@qq.com", "job_title": "副教授", "abstracts": null, "directions": null, "education_experience": null, "work_experience": null, "patent": null, "project": null, "award": null, "social_job": null, "picture": "https://nxy.ybu.edu.cn/__local/D/B8/89/8FF7B18B3B9A28696C74B411572_B6C6AD48_6468.jpg", "education": "研究生", "qualification": "博士", "job_information": 1, "responsibilities": null, "office_address": null}, {"name": "崔正云", "school_id": 10, "college_id": 87, "phone": null, "email": "zycui@ybu.edu.cn", "job_title": "讲师", "abstracts": null, "directions": null, "education_experience": null, "work_experience": null, "patent": null, "project": null, "award": null, "social_job": null, "picture": "https://nxy.ybu.edu.cn/__local/4/7B/FE/3FCE874A05D1BD0AB940C8AC86D_BC38FAE6_5AF2.jpg", "education": "研究生", "qualification": "博士", "job_information": 1, "responsibilities": null, "office_address": null}, {"name": "崔泰花", "school_id": 10, "college_id": 87, "phone": "0433-2435576,13341526011", "email": "lich@ybu.edu.cn", "job_title": "实验师", "abstracts": null, "directions": null, "education_experience": null, "work_experience": null, "patent": null, "project": null, "award": null, "social_job": null, "picture": "https://nxy.ybu.edu.cn/__local/9/76/1B/EF763308FF2EE67FF08FDB9B0E5_82BD3281_76D8.jpg", "education": "本科", "qualification": "学士", "job_information": 1, "responsibilities": null, "office_address": null}, {"name": "崔福顺", "school_id": 10, "college_id": 87, "phone": "0433-2435616", "email": "0000005351@ybu.edu.cn", "job_title": "副教授", "abstracts": null, "directions": null, "education_experience": null, "work_experience": null, "patent": null, "project": null, "award": null, "social_job": null, "picture": null, "education": "研究生", "qualification": "硕士", "job_information": 1, "responsibilities": null, "office_address": null}, {"name": "崔莲花", "school_id": 10, "college_id": 87, "phone": "18243330002", "email": "cuilianhua@ybu.edu.cn", "job_title": "副教授", "abstracts": null, "directions": null, "education_experience": null, "work_experience": null, "patent": null, "project": null, "award": null, "social_job": null, "picture": "https://nxy.ybu.edu.cn/__local/A/E1/07/A490302D47E5E9DA017C6271707_8CDAD4EE_A76C.jpg", "education": "研究生", "qualification": "博士", "job_information": 1, "responsibilities": null, "office_address": null}, {"name": "康锦丹", "school_id": 10, "college_id": 87, "phone": null, "email": "jdkang@ybu.edu.cn", "job_title": "教授", "abstracts": null, "directions": null, "education_experience": null, "work_experience": null, "patent": null, "project": null, "award": null, "social_job": null, "picture": "https://nxy.ybu.edu.cn/__local/4/75/01/57F51985724EF1E5B3A5E7BFDBD_6C5AB49D_7CF7.jpg", "education": "研究生", "qualification": "博士", "job_information": 1, "responsibilities": null, "office_address": null}, {"name": "廉美兰", "school_id": 10, "college_id": 87, "phone": "0433-2435625", "email": "mllian@ybu.edu.cn", "job_title": "教授", "abstracts": null, "directions": null, "education_experience": null, "work_experience": null, "patent": null, "project": null, "award": null, "social_job": null, "picture": "https://nxy.ybu.edu.cn/__local/2/7C/34/0074724BFD564BD34F42EE9D712_6AA46DFE_135FD.jpg", "education": "研究生", "qualification": "博士", "job_information": 1, "responsibilities": null, "office_address": null}, {"name": "张华", "school_id": 10, "college_id": 87, "phone": "15567600103", "email": "zhanghua@ybu.edu.cn", "job_title": "讲师", "abstracts": null, "directions": null, "education_experience": null, "work_experience": null, "patent": null, "project": null, "award": null, "social_job": null, "picture": "https://nxy.ybu.edu.cn/__local/B/55/D7/F4F718A2FA63BC12BB6BC7D19C4_D2863842_C7AA.jpg", "education": "研究生", "qualification": "博士", "job_information": 1, "responsibilities": null, "office_address": null}, {"name": "张敏", "school_id": 10, "college_id": 87, "phone": null, "email": "zhangmin@ybu.edu.cn", "job_title": "教授", "abstracts": null, "directions": null, "education_experience": null, "work_experience": null, "patent": null, "project": null, "award": null, "social_job": null, "picture": null, "education": "研究生", "qualification": "硕士", "job_information": 1, "responsibilities": null, "office_address": null}, {"name": "张美淑", "school_id": 10, "college_id": 87, "phone": "13844314931", "email": "244798469@qq.com", "job_title": "高级实验师", "abstracts": null, "directions": null, "education_experience": null, "work_experience": null, "patent": null, "project": null, "award": null, "social_job": null, "picture": "https://nxy.ybu.edu.cn/__local/2/E2/BA/84E34912CB693A111882009DDB9_119014AA_6820.jpg", "education": "本科", "qualification": "学士", "job_information": 1, "responsibilities": null, "office_address": null}, {"name": "张雪梅", "school_id": 10, "college_id": 87, "phone": null, "email": "zhangxm@ybu.edu.cn", "job_title": "教授", "abstracts": null, "directions": null, "education_experience": null, "work_experience": null, "patent": null, "project": null, "award": null, "social_job": null, "picture": "https://nxy.ybu.edu.cn/__local/6/4E/42/38910F4DBA4944F161765E4A344_08BB6BB9_2668.jpg", "education": "研究生", "qualification": "博士", "job_information": 1, "responsibilities": null, "office_address": null}, {"name": "张雪莲", "school_id": 10, "college_id": 87, "phone": "0433-2435548", "email": "jwzxl@ybu.edu.cn", "job_title": "实验师", "abstracts": null, "directions": null, "education_experience": null, "work_experience": null, "patent": null, "project": null, "award": null, "social_job": null, "picture": "https://nxy.ybu.edu.cn/__local/C/2C/99/6B83B42C078F4B6F82627CB09E7_72A22965_5DBD.jpg", "education": "研究生", "qualification": "硕士", "job_information": 1, "responsibilities": null, "office_address": null}, {"name": "徐寿军", "school_id": 10, "college_id": 87, "phone": "13500637676", "email": "shoujun-xu@163.com", "job_title": "教授", "abstracts": null, "directions": null, "education_experience": null, "work_experience": null, "patent": null, "project": null, "award": null, "social_job": null, "picture": null, "education": "研究生", "qualification": "博士", "job_information": 1, "responsibilities": null, "office_address": null}, {"name": "徐济责", "school_id": 10, "college_id": 87, "phone": "15981106550", "email": "xujz802@nenu.edu.cn", "job_title": "教授", "abstracts": null, "directions": null, "education_experience": null, "work_experience": null, "patent": null, "project": null, "award": null, "social_job": null, "picture": "https://nxy.ybu.edu.cn/__local/7/AA/19/5E4931012D49DBDE0709046519A_5F983972_530F.png", "education": "研究生", "qualification": "博士", "job_information": 1, "responsibilities": null, "office_address": null}, {"name": "徐红艳", "school_id": 10, "college_id": 87, "phone": "13944709169", "email": "xuhongyan@ybu.edu.cn", "job_title": "教授", "abstracts": null, "directions": null, "education_experience": null, "work_experience": null, "patent": null, "project": null, "award": null, "social_job": null, "picture": "https://nxy.ybu.edu.cn/__local/A/A7/A7/2A67CC6D0AF44E0E03E6FB23023_295E56A3_B9B38.png", "education": "研究生", "qualification": "博士", "job_information": 1, "responsibilities": null, "office_address": null}, {"name": "戢爽", "school_id": 10, "college_id": 87, "phone": "0433-2435596", "email": "jishuang@ybu.edu.cn", "job_title": "讲师", "abstracts": null, "directions": null, "education_experience": null, "work_experience": null, "patent": null, "project": null, "award": null, "social_job": null, "picture": "https://nxy.ybu.edu.cn/__local/3/67/30/18A07CA8DADCB6E0D31EFB3A75B_9754C593_6F39.jpg", "education": "研究生", "qualification": "博士", "job_information": 1, "responsibilities": null, "office_address": null}, {"name": "文宇萍", "school_id": 10, "college_id": 87, "phone": "13944370266", "email": "0000008711@ybu.edu.cn", "job_title": "实验师", "abstracts": null, "directions": null, "education_experience": null, "work_experience": null, "patent": null, "project": null, "award": null, "social_job": null, "picture": "https://nxy.ybu.edu.cn/__local/8/86/BD/E0C675AE6E6DA7792FE18EFB3FE_DC3673A2_567A.jpg", "education": "研究生", "qualification": "硕士", "job_information": 1, "responsibilities": null, "office_address": null}, {"name": "方南洙", "school_id": 10, "college_id": 87, "phone": "13844392153", "email": "nzfang@ybu.edu.cn", "job_title": "教授", "abstracts": null, "directions": null, "education_experience": null, "work_experience": null, "patent": null, "project": null, "award": null, "social_job": null, "picture": "https://nxy.ybu.edu.cn/__local/1/AC/0A/3153CFCA640078FEB6C1CD0DF5C_D0126A8E_17BA5.jpg", "education": "研究生", "qualification": "博士", "job_information": 1, "responsibilities": null, "office_address": null}, {"name": "曹丽", "school_id": 10, "college_id": 87, "phone": "15714438666,0433-2435571", "email": "lcao@ybu.edu.cn", "job_title": "副教授", "abstracts": null, "directions": null, "education_experience": null, "work_experience": null, "patent": null, "project": null, "award": null, "social_job": null, "picture": "https://nxy.ybu.edu.cn/__local/C/3A/EB/1D887ABD5E4C3EB6FD2E41A2B94_743E0452_6102.jpg", "education": "研究生", "qualification": "博士", "job_information": 1, "responsibilities": null, "office_address": null}, {"name": "朴世领", "school_id": 10, "college_id": 87, "phone": "0433-2733375", "email": "pslpjj@ybu.edu.cn", "job_title": "教授", "abstracts": null, "directions": null, "education_experience": null, "work_experience": null, "patent": null, "project": null, "award": null, "social_job": null, "picture": "https://nxy.ybu.edu.cn/__local/8/71/D2/16FFA3F87DBB3A118719531FAE9_B17824E9_27979.jpg", "education": "研究生", "qualification": "硕士", "job_information": 1, "responsibilities": null, "office_address": null}, {"name": "朴仁哲", "school_id": 10, "college_id": 87, "phone": "13944762331", "email": "rzpiao@ybu.edu.cn", "job_title": "教授", "abstracts": null, "directions": null, "education_experience": null, "work_experience": null, "patent": null, "project": null, "award": null, "social_job": null, "picture": "https://nxy.ybu.edu.cn/__local/F/DD/A2/DCC68DA731514C09465355CC488_8E19F508_6FC9.jpg", "education": "研究生", "qualification": "博士", "job_information": 1, "responsibilities": null, "office_address": null}, {"name": "朴政霖", "school_id": 10, "college_id": 87, "phone": "18843331399", "email": "0000008765@ybu.edu.cn", "job_title": "讲师", "abstracts": null, "directions": null, "education_experience": null, "work_experience": null, "patent": null, "project": null, "award": null, "social_job": null, "picture": "https://nxy.ybu.edu.cn/__local/5/32/AF/2293631BF4C00C4C07F14CBDE12_4B11EC54_21AC.jpg", "education": "研究生", "qualification": "博士", "job_information": 1, "responsibilities": null, "office_address": null}, {"name": "朴政霖", "school_id": 10, "college_id": 87, "phone": "0433-2733279", "email": "aglou@ybu.edu.cn", "job_title": "讲师", "abstracts": null, "directions": null, "education_experience": null, "work_experience": null, "patent": null, "project": null, "award": null, "social_job": null, "picture": "https://nxy.ybu.edu.cn/__local/7/BF/44/5D06981FDE5B419CCBAC2F57233_F392A656_506C.jpg", "education": "研究生", "qualification": "博士", "job_information": 1, "responsibilities": null, "office_address": null}, {"name": "朴文华", "school_id": 10, "college_id": 87, "phone": "18843338822", "email": "whpiao@ybu.edu.cn", "job_title": "副教授", "abstracts": null, "directions": null, "education_experience": null, "work_experience": null, "patent": null, "project": null, "award": null, "social_job": null, "picture": "https://nxy.ybu.edu.cn/__local/A/98/64/75B08B04BE55C7F95B868AF1A0C_1F5919AF_B623.jpg", "education": "研究生", "qualification": "博士", "job_information": 1, "responsibilities": null, "office_address": null}, {"name": "朴明淑", "school_id": 10, "college_id": 87, "phone": "13894383408", "email": "1739443260@qq.com", "job_title": "实验师", "abstracts": null, "directions": null, "education_experience": null, "work_experience": null, "patent": null, "project": null, "award": null, "social_job": null, "picture": "https://nxy.ybu.edu.cn/__local/2/36/C4/1B8E1604F2DDE4D4E030BD5F2DE_19F1DDEA_5F14.jpg", "education": "本科", "qualification": "学士", "job_information": 1, "responsibilities": null, "office_address": null}, {"name": "朴春香", "school_id": 10, "college_id": 87, "phone": null, "email": "cxpiao@ybu.edu.cn", "job_title": "副教授", "abstracts": null, "directions": null, "education_experience": null, "work_experience": null, "patent": null, "project": null, "award": null, "social_job": null, "picture": "https://nxy.ybu.edu.cn/__local/4/AD/F7/3DDBCB9627E43FB1351F1E099DF_63EB1C09_60FF.jpg", "education": "研究生", "qualification": "博士", "job_information": 1, "responsibilities": null, "office_address": null}, {"name": "朴炫春", "school_id": 10, "college_id": 87, "phone": "0433-2435747", "email": "nyypxc@ybu.edu.cn", "job_title": "教授", "abstracts": null, "directions": null, "education_experience": null, "work_experience": null, "patent": null, "project": null, "award": null, "social_job": null, "picture": "https://nxy.ybu.edu.cn/__local/A/A4/57/05EC6371C715DF80C83A060ABD2_E41C2681_12005.jpg", "education": "研究生", "qualification": "博士", "job_information": 1, "responsibilities": null, "office_address": null}, {"name": "朴英俊", "school_id": 10, "college_id": 87, "phone": "18901339104", "email": "0000008590@ybu.edu.cn", "job_title": "工程师", "abstracts": null, "directions": null, "education_experience": null, "work_experience": null, "patent": null, "project": null, "award": null, "social_job": null, "picture": "https://nxy.ybu.edu.cn/__local/F/2D/53/A78C5654827899C4BBB6B56554E_49B06B96_5E2C.jpg", "education": "研究生", "qualification": "硕士", "job_information": 1, "responsibilities": null, "office_address": null}, {"name": "朴锦", "school_id": 10, "college_id": 87, "phone": "0433-2435586", "email": "piaojin@ybu.edu.cn", "job_title": "副教授", "abstracts": null, "directions": null, "education_experience": null, "work_experience": null, "patent": null, "project": null, "award": null, "social_job": null, "picture": "https://nxy.ybu.edu.cn/__local/8/5A/04/FEA8AFF8139338B8D55F75BC1F6_63536E1D_5807.jpg", "education": "研究生", "qualification": "博士", "job_information": 1, "responsibilities": null, "office_address": null}, {"name": "权赫春", "school_id": 10, "college_id": 87, "phone": "15004330172", "email": "hcquan@ybu.edu.cn", "job_title": "教授", "abstracts": null, "directions": null, "education_experience": null, "work_experience": null, "patent": null, "project": null, "award": null, "social_job": null, "picture": "https://nxy.ybu.edu.cn/__local/E/16/7C/1897DE89A0F2EBB4F3207245702_77141056_2A5B6.jpg", "education": "研究生", "qualification": "博士", "job_information": 1, "responsibilities": null, "office_address": null}, {"name": "权跃", "school_id": 10, "college_id": 87, "phone": "15844377891", "email": "quanyue@ybu.edu.cn", "job_title": "副教授", "abstracts": null, "directions": null, "education_experience": null, "work_experience": null, "patent": null, "project": null, "award": null, "social_job": null, "picture": "https://nxy.ybu.edu.cn/__local/1/37/52/08B7F361F464CB345173BA63D56_6ED658A9_99250.png", "education": "研究生", "qualification": "博士", "job_information": 1, "responsibilities": null, "office_address": null}, {"name": "李光春", "school_id": 10, "college_id": 87, "phone": "0433-2435552", "email": "gcli@ybu.edu.cn", "job_title": "讲师", "abstracts": null, "directions": null, "education_experience": null, "work_experience": null, "patent": null, "project": null, "award": null, "social_job": null, "picture": "https://nxy.ybu.edu.cn/__local/C/65/E5/C87D2ECA79E477C04A79C978F00_A6D4B7C1_4CA9.jpg", "education": "研究生", "qualification": "博士", "job_information": 1, "responsibilities": null, "office_address": null}, {"name": "李刚", "school_id": 10, "college_id": 87, "phone": "13504311691", "email": "ligang6311@126.com", "job_title": "研究员", "abstracts": null, "directions": null, "education_experience": null, "work_experience": null, "patent": null, "project": null, "award": null, "social_job": null, "picture": "https://nxy.ybu.edu.cn/__local/5/95/E2/7D60EB49AEF1953C85D5632CD8F_83C49E13_17349.jpg", "education": "研究生", "qualification": "博士", "job_information": 1, "responsibilities": null, "office_address": null}, {"name": "李太元", "school_id": 10, "college_id": 87, "phone": "0433-2435593", "email": "tyli@ybu.edu.cn", "job_title": "教授", "abstracts": null, "directions": null, "education_experience": null, "work_experience": null, "patent": null, "project": null, "award": null, "social_job": null, "picture": "https://nxy.ybu.edu.cn/system/editor/ueditor_news/themes/default/images/spacer.gif", "education": "研究生", "qualification": "硕士", "job_information": 1, "responsibilities": null, "office_address": null}, {"name": "李官浩", "school_id": 10, "college_id": 87, "phone": null, "email": "ghli@ybu.edu.cn", "job_title": "教授", "abstracts": null, "directions": null, "education_experience": null, "work_experience": null, "patent": null, "project": null, "award": null, "social_job": null, "picture": "https://nxy.ybu.edu.cn/__local/E/F8/05/D3B5585807D742123C81CD6BB7E_2128F023_E954.png", "education": "研究生", "qualification": "博士", "job_information": 1, "responsibilities": null, "office_address": null}, {"name": "李强", "school_id": 10, "college_id": 87, "phone": "13844316897", "email": "liqiang8589@ybuedu.cn", "job_title": "讲师", "abstracts": null, "directions": null, "education_experience": null, "work_experience": null, "patent": null, "project": null, "award": null, "social_job": null, "picture": "https://nxy.ybu.edu.cn/__local/1/98/36/34B478192D4E64F919C4C05F38A_85C2D7F4_7341.jpg", "education": "研究生", "qualification": "博士", "job_information": 1, "responsibilities": null, "office_address": null}, {"name": "李德允", "school_id": 10, "college_id": 87, "phone": null, "email": "dyli@ybu.edu.cn", "job_title": "教授", "abstracts": null, "directions": null, "education_experience": null, "work_experience": null, "patent": null, "project": null, "award": null, "social_job": null, "picture": "https://nxy.ybu.edu.cn/__local/2/53/0D/FB952DA547DF3FA8362152AC011_8D568AAE_18C3A.png", "education": "研究生", "qualification": "博士", "job_information": 1, "responsibilities": null, "office_address": null}, {"name": "李成云", "school_id": 10, "college_id": 87, "phone": "13943322092", "email": "licy@ybu.edu.cn", "job_title": "副教授", "abstracts": null, "directions": null, "education_experience": null, "work_experience": null, "patent": null, "project": null, "award": null, "social_job": null, "picture": "https://nxy.ybu.edu.cn/__local/E/B9/B3/4D00392576D880FCF1723C199F9_18A86C38_6D7B.jpg", "education": "研究生", "qualification": "博士", "job_information": 1, "responsibilities": null, "office_address": null}, {"name": "李文学", "school_id": 10, "college_id": 87, "phone": "13944306810", "email": "Liwx@ybu.edu.cn", "job_title": "副教授", "abstracts": null, "directions": null, "education_experience": null, "work_experience": null, "patent": null, "project": null, "award": null, "social_job": null, "picture": "https://nxy.ybu.edu.cn/__local/D/01/E4/B72DCA6150D50C7E70A1F6A571C_CEC89357_29778.jpg", "education": "研究生", "qualification": "博士", "job_information": 1, "responsibilities": null, "office_address": null}, {"name": "李松月", "school_id": 10, "college_id": 87, "phone": "13844702168", "email": "sylee@ybu.edu.cn", "job_title": "实验师", "abstracts": null, "directions": null, "education_experience": null, "work_experience": null, "patent": null, "project": null, "award": null, "social_job": null, "picture": "https://nxy.ybu.edu.cn/__local/A/06/FB/C67EA30274ED1CF3F65D5159836_6792F9DA_6829.jpg", "education": "研究生", "qualification": "博士", "job_information": 1, "responsibilities": null, "office_address": null}, {"name": "李海峰", "school_id": 10, "college_id": 87, "phone": "0433-2435609", "email": "lihaifeng@ybu.edu.cn", "job_title": "副教授", "abstracts": null, "directions": null, "education_experience": null, "work_experience": null, "patent": null, "project": null, "award": null, "social_job": null, "picture": "https://nxy.ybu.edu.cn/__local/6/7A/28/1798B260718954228BE3BF2CE8A_4FB3560E_642C.jpg", "education": "研究生", "qualification": "硕士", "job_information": 1, "responsibilities": null, "office_address": null}, {"name": "李熙英", "school_id": 10, "college_id": 87, "phone": "13894302962", "email": "xyli@ybu.edu.cn", "job_title": "教授", "abstracts": null, "directions": null, "education_experience": null, "work_experience": null, "patent": null, "project": null, "award": null, "social_job": null, "picture": "https://nxy.ybu.edu.cn/__local/7/BE/69/13CD19C57E47542AF0FF7A9833E_D3AECB80_1E64E.png", "education": "研究生", "qualification": "博士", "job_information": 1, "responsibilities": null, "office_address": null}, {"name": "李红梅", "school_id": 10, "college_id": 87, "phone": "0433-2435591", "email": "hmli2018@ybu.edu.cn", "job_title": "讲师", "abstracts": null, "directions": null, "education_experience": null, "work_experience": null, "patent": null, "project": null, "award": null, "social_job": null, "picture": "https://nxy.ybu.edu.cn/__local/F/97/EB/613F8B3A36D0381F16D394BE049_5A545E98_3CA7.jpg", "education": "研究生", "qualification": "博士", "job_information": 1, "responsibilities": null, "office_address": null}, {"name": "李美善", "school_id": 10, "college_id": 87, "phone": "13843358772", "email": "mshli@ybu.edu.cn", "job_title": "高级实验师", "abstracts": null, "directions": null, "education_experience": null, "work_experience": null, "patent": null, "project": null, "award": null, "social_job": null, "picture": "https://nxy.ybu.edu.cn/__local/9/47/3B/53C20D396CB6230B513EB01787D_76D6207D_7CA2.jpg", "education": "研究生", "qualification": "博士", "job_information": 1, "responsibilities": null, "office_address": null}, {"name": "李美阳", "school_id": 10, "college_id": 87, "phone": null, "email": null, "job_title": "讲师", "abstracts": null, "directions": null, "education_experience": null, "work_experience": null, "patent": null, "project": null, "award": null, "social_job": null, "picture": "https://nxy.ybu.edu.cn/__local/7/1B/0A/8985AC0A4EF5450096851B84B37_B744C95B_7EAB.png", "education": "研究生", "qualification": "博士", "job_information": 1, "responsibilities": null, "office_address": null}, {"name": "李翔国", "school_id": 10, "college_id": 87, "phone": "0433-2435563", "email": "2420187676@qq.com", "job_title": "讲师", "abstracts": null, "directions": null, "education_experience": null, "work_experience": null, "patent": null, "project": null, "award": null, "social_job": null, "picture": "https://nxy.ybu.edu.cn/__local/1/26/25/0A138D240A5A3E8A7C147D97540_517936C2_6883.jpg", "education": "研究生", "qualification": "博士", "job_information": 1, "responsibilities": null, "office_address": null}, {"name": "李艳茹", "school_id": 10, "college_id": 87, "phone": null, "email": null, "job_title": "高级实验师", "abstracts": null, "directions": null, "education_experience": null, "work_experience": null, "patent": null, "project": null, "award": null, "social_job": null, "picture": "https://nxy.ybu.edu.cn/__local/9/EC/21/139A9A29FE615A1FE0337B7AC22_87A62DC1_71FD7.png", "education": "本科", "qualification": "学士", "job_information": 1, "responsibilities": null, "office_address": null}, {"name": "李范洙", "school_id": 10, "college_id": 87, "phone": "13596529778", "email": "fzli@ybu.edu.cn", "job_title": "副教授", "abstracts": null, "directions": null, "education_experience": null, "work_experience": null, "patent": null, "project": null, "award": null, "social_job": null, "picture": "https://nxy.ybu.edu.cn/__local/B/5B/42/3E8163C913BCEC288A2A4D06C01_F83E6F69_4F67.jpg", "education": "研究生", "qualification": "博士", "job_information": 1, "responsibilities": null, "office_address": null}, {"name": "李葵花", "school_id": 10, "college_id": 87, "phone": "13943371560", "email": "khli@ybu.edu.cn", "job_title": "副教授", "abstracts": null, "directions": null, "education_experience": null, "work_experience": null, "patent": null, "project": null, "award": null, "social_job": null, "picture": "https://nxy.ybu.edu.cn/__local/B/ED/90/858D5894C4A42EC1A201879F7D2_D4CD5C68_4DD6.jpg", "education": "研究生", "qualification": "博士", "job_information": 1, "responsibilities": null, "office_address": null}, {"name": "李虎林", "school_id": 10, "college_id": 87, "phone": "13843363153", "email": "Lhlsym@ybu.edu.cn", "job_title": "教授", "abstracts": null, "directions": null, "education_experience": null, "work_experience": null, "patent": null, "project": null, "award": null, "social_job": null, "picture": "https://nxy.ybu.edu.cn/__local/B/65/12/A9128E9E05BC94B3D4019ACC652_8BD6F213_6056.jpg", "education": "研究生", "qualification": "博士", "job_information": 1, "responsibilities": null, "office_address": null}, {"name": "李钟淑", "school_id": 10, "college_id": 87, "phone": "0433-2435526", "email": "zhangmin@ybu.edu.cn", "job_title": "教授", "abstracts": null, "directions": null, "education_experience": null, "work_experience": null, "patent": null, "project": null, "award": null, "social_job": null, "picture": "https://nxy.ybu.edu.cn/__local/6/92/47/1FAE0899DB0108874B0482A5B46_01C80656_5D29.jpg", "education": "研究生", "qualification": "博士", "job_information": 1, "responsibilities": null, "office_address": null}, {"name": "李铉军", "school_id": 10, "college_id": 87, "phone": "0433-2435616", "email": "fzli@ybu.edu.cn", "job_title": "讲师", "abstracts": null, "directions": null, "education_experience": null, "work_experience": null, "patent": null, "project": null, "award": null, "social_job": null, "picture": "https://nxy.ybu.edu.cn/__local/9/6A/7C/7C8379ED7F7CDBB7C1FF54ADABB_4557599A_4384.jpg", "education": "研究生", "qualification": "博士", "job_information": 1, "responsibilities": null, "office_address": null}, {"name": "李香子", "school_id": 10, "college_id": 87, "phone": "0433-2435628", "email": "lxz@ybu.edu.cn", "job_title": "教授", "abstracts": null, "directions": null, "education_experience": null, "work_experience": null, "patent": null, "project": null, "award": null, "social_job": null, "picture": "https://nxy.ybu.edu.cn/__local/E/55/EF/6E7C247CF587797B7E705E3FD0C_AB80DF9E_6C45.jpg", "education": "研究生", "qualification": "博士", "job_information": 1, "responsibilities": null, "office_address": null}, {"name": "杨咏洁", "school_id": 10, "college_id": 87, "phone": "15585557188", "email": "yjyang@ybu.edu.cn", "job_title": "副教授", "abstracts": null, "directions": null, "education_experience": null, "work_experience": null, "patent": null, "project": null, "award": null, "social_job": null, "picture": "https://nxy.ybu.edu.cn/__local/4/59/BF/C2AB4B5AED7FFF5A566D28F7FE2_27B594C3_8EC5.png", "education": "研究生", "qualification": "博士", "job_information": 1, "responsibilities": null, "office_address": null}, {"name": "柳海星", "school_id": 10, "college_id": 87, "phone": null, "email": "hxliu@ybu.edu.cn", "job_title": "副教授", "abstracts": null, "directions": null, "education_experience": null, "work_experience": null, "patent": null, "project": null, "award": null, "social_job": null, "picture": "https://nxy.ybu.edu.cn/__local/4/51/86/D59A2F5A6EC72839C3A3603BDD5_A6E971E2_192E4.jpg", "education": "研究生", "qualification": "博士", "job_information": 1, "responsibilities": null, "office_address": null}, {"name": "梁成云", "school_id": 10, "college_id": 87, "phone": "13843392005", "email": "cyliang@ybu.edu.cn", "job_title": "教授", "abstracts": null, "directions": null, "education_experience": null, "work_experience": null, "patent": null, "project": null, "award": null, "social_job": null, "picture": "https://nxy.ybu.edu.cn/__local/4/09/5B/1639A594F7E4F881D1C04D03515_03960C83_4E0A.jpg", "education": "研究生", "qualification": "博士", "job_information": 1, "responsibilities": null, "office_address": null}, {"name": "梁晚枫", "school_id": 10, "college_id": 87, "phone": "13704461302", "email": "liangwf@ybu.edu.cn", "job_title": "教授", "abstracts": null, "directions": null, "education_experience": null, "work_experience": null, "patent": null, "project": null, "award": null, "social_job": null, "picture": "https://nxy.ybu.edu.cn/__local/9/66/4A/C9A3A871EB6DAA7A04CB7DAE850_8C1A9687_7B3F.jpg", "education": "研究生", "qualification": "硕士", "job_information": 1, "responsibilities": null, "office_address": null}, {"name": "梁运江", "school_id": 10, "college_id": 87, "phone": "13944709192", "email": "lyjlluo@ybu.edu.cn", "job_title": "副教授", "abstracts": null, "directions": null, "education_experience": null, "work_experience": null, "patent": null, "project": null, "award": null, "social_job": null, "picture": "https://nxy.ybu.edu.cn/__local/5/90/E8/F3E6FB39370B6D5FA3A42B30BF2_C533916F_27F3.jpg", "education": "研究生", "qualification": "博士", "job_information": 1, "responsibilities": null, "office_address": null}, {"name": "牟柏德", "school_id": 10, "college_id": 87, "phone": "13944309069", "email": "165248122@qq.com", "job_title": "讲师", "abstracts": null, "directions": null, "education_experience": null, "work_experience": null, "patent": null, "project": null, "award": null, "social_job": null, "picture": "https://nxy.ybu.edu.cn/__local/F/7B/F4/359A616DA277E5F4214DCAE2838_1FEAB592_BA51.jpg", "education": "研究生", "qualification": "硕士", "job_information": 1, "responsibilities": null, "office_address": null}, {"name": "王全英", "school_id": 10, "college_id": 87, "phone": "15004315056", "email": "qywang@iga.ac.cn", "job_title": "教授", "abstracts": null, "directions": null, "education_experience": null, "work_experience": null, "patent": null, "project": null, "award": null, "social_job": null, "picture": "https://nxy.ybu.edu.cn/__local/1/8F/A7/9E363143BF2470071CC6D87FDE3_8C7A5F0B_7618.png", "education": "研究生", "qualification": "博士", "job_information": 1, "responsibilities": null, "office_address": null}, {"name": "王妍", "school_id": 10, "college_id": 87, "phone": "13324338181", "email": "2676806621@qq.com", "job_title": "副教授", "abstracts": null, "directions": null, "education_experience": null, "work_experience": null, "patent": null, "project": null, "award": null, "social_job": null, "picture": "https://nxy.ybu.edu.cn/__local/6/83/F5/DC33494442059420368F7DA28B7_08C5A856_8202.jpg", "education": "研究生", "qualification": "博士", "job_information": 1, "responsibilities": null, "office_address": null}, {"name": "王娟", "school_id": 10, "college_id": 87, "phone": "13694330981", "email": "wangjuan@ybu.edu.cn", "job_title": "副教授", "abstracts": null, "directions": null, "education_experience": null, "work_experience": null, "patent": null, "project": null, "award": null, "social_job": null, "picture": "https://nxy.ybu.edu.cn/__local/A/E9/3F/4CAC8879392205390848A3E0E94_66468D66_1B212.png", "education": "研究生", "qualification": "博士", "job_information": 1, "responsibilities": null, "office_address": null}, {"name": "王秀华", "school_id": 10, "college_id": 87, "phone": "18743009866", "email": "xiuhauwang613@ybu.edu.cn", "job_title": "讲师", "abstracts": null, "directions": null, "education_experience": null, "work_experience": null, "patent": null, "project": null, "award": null, "social_job": null, "picture": "https://nxy.ybu.edu.cn/__local/E/A7/40/44871F85E117CF1582C04C455A1_4F3C6A23_1CD90.png", "education": "研究生", "qualification": "博士", "job_information": 1, "responsibilities": null, "office_address": null}, {"name": "申明哲", "school_id": 10, "college_id": 87, "phone": "0443-2435569", "email": "shen0224@ybu.edu.cn", "job_title": "副教授", "abstracts": null, "directions": null, "education_experience": null, "work_experience": null, "patent": null, "project": null, "award": null, "social_job": null, "picture": "https://nxy.ybu.edu.cn/__local/4/0B/4D/9A4BC1BC2AEBF234897264D286A_CE88510F_2DEF.jpg", "education": "研究生", "qualification": "博士", "job_information": 1, "responsibilities": null, "office_address": null}, {"name": "申明哲", "school_id": 10, "college_id": 87, "phone": "0433-2435542", "email": "shen0224@ybu.edu.com", "job_title": "副教授", "abstracts": null, "directions": null, "education_experience": null, "work_experience": null, "patent": null, "project": null, "award": null, "social_job": null, "picture": "https://nxy.ybu.edu.cn/__local/E/12/E8/00DDA62C02316659EECEB357C76_4737DCAF_12525.jpg", "education": "研究生", "qualification": "博士", "job_information": 1, "responsibilities": null, "office_address": null}, {"name": "罗广军", "school_id": 10, "college_id": 87, "phone": "13944390798", "email": "Gjluo999@163.com", "job_title": "副教授", "abstracts": null, "directions": null, "education_experience": null, "work_experience": null, "patent": null, "project": null, "award": null, "social_job": null, "picture": "https://nxy.ybu.edu.cn/__local/4/DC/D3/FFF8D77B467A23F44633F6C0017_8B4DA495_C31A1.jpg", "education": "研究生", "qualification": "硕士", "job_information": 1, "responsibilities": null, "office_address": null}, {"name": "耿春银", "school_id": 10, "college_id": 87, "phone": "0433-2435596", "email": "cygeng1011@163.com", "job_title": "副教授", "abstracts": null, "directions": null, "education_experience": null, "work_experience": null, "patent": null, "project": null, "award": null, "social_job": null, "picture": "https://nxy.ybu.edu.cn/__local/C/8E/0D/0FB013DA67E207C8ADB59CCB614_B9FC2610_3DE2B.jpg", "education": "研究生", "qualification": "博士", "job_information": 1, "responsibilities": null, "office_address": null}, {"name": "范丽清", "school_id": 10, "college_id": 87, "phone": null, "email": "lqfan@ybu.edu.cn", "job_title": "副教授", "abstracts": null, "directions": null, "education_experience": null, "work_experience": null, "patent": null, "project": null, "award": null, "social_job": null, "picture": "https://nxy.ybu.edu.cn/__local/2/C0/39/8A935B209E7A7A52485CB61EE32_ADF949FD_3609.jpg", "education": "研究生", "qualification": "博士", "job_information": 1, "responsibilities": null, "office_address": null}, {"name": "荣立苹", "school_id": 10, "college_id": 87, "phone": "0433-2435554", "email": "rongliping2013@163.com", "job_title": "副教授", "abstracts": null, "directions": null, "education_experience": null, "work_experience": null, "patent": null, "project": null, "award": null, "social_job": null, "picture": "https://nxy.ybu.edu.cn/__local/0/61/F0/D4C949A6DACDFE2BD87EED9D0E4_CA1D747E_73CC.jpg", "education": "研究生", "qualification": "博士", "job_information": 1, "responsibilities": null, "office_address": null}, {"name": "董微巍", "school_id": 10, "college_id": 87, "phone": "13904466102", "email": "wwdong@ybu.edu.cn", "job_title": "副教授", "abstracts": null, "directions": null, "education_experience": null, "work_experience": null, "patent": null, "project": null, "award": null, "social_job": null, "picture": "https://nxy.ybu.edu.cn/__local/9/1B/52/F31E696CF7AFDC4972AB3EF96F8_75B001EB_5E266.png", "education": "研究生", "qualification": "博士", "job_information": 1, "responsibilities": null, "office_address": null}, {"name": "董英山", "school_id": 10, "college_id": 87, "phone": "13944809567", "email": "ysdong@cjaas.com", "job_title": "研究员", "abstracts": null, "directions": null, "education_experience": null, "work_experience": null, "patent": null, "project": null, "award": null, "social_job": null, "picture": "https://nxy.ybu.edu.cn/__local/9/AB/73/94B2741639A217C7F08E800D460_4289DDB6_1EE3B.jpg", "education": "研究生", "qualification": "博士", "job_information": 1, "responsibilities": null, "office_address": null}, {"name": "蔡红光", "school_id": 10, "college_id": 87, "phone": "15584441606", "email": "caihongguang1981@163.com", "job_title": "研究员", "abstracts": null, "directions": null, "education_experience": null, "work_experience": null, "patent": null, "project": null, "award": null, "social_job": null, "picture": "https://nxy.ybu.edu.cn/__local/2/77/CF/1C3BD982BFC98D79B664F191845_492C30FD_422E.jpg", "education": "研究生", "qualification": "博士", "job_information": 1, "responsibilities": null, "office_address": null}, {"name": "蔡锦顺", "school_id": 10, "college_id": 87, "phone": "13844390670", "email": "jinshuncai@163.com", "job_title": "副教授", "abstracts": null, "directions": null, "education_experience": null, "work_experience": null, "patent": null, "project": null, "award": null, "social_job": null, "picture": "https://nxy.ybu.edu.cn/__local/6/A3/52/55ACF6A58A5AC7EA0895719C9CF_6543ACD3_AB61.jpg", "education": "研究生", "qualification": "博士", "job_information": 1, "responsibilities": null, "office_address": null}, {"name": "薛书江", "school_id": 10, "college_id": 87, "phone": "0433-2435539", "email": "sjxue@ybu.edu.cn", "job_title": "副教授", "abstracts": null, "directions": null, "education_experience": null, "work_experience": null, "patent": null, "project": null, "award": null, "social_job": null, "picture": "https://nxy.ybu.edu.cn/__local/6/D4/A5/59A1D8EA3FDF99ED9ED43AD45E5_B2E26794_5027.jpg", "education": "研究生", "qualification": "博士", "job_information": 1, "responsibilities": null, "office_address": null}, {"name": "许应天", "school_id": 10, "college_id": 87, "phone": "13844360446", "email": "ytxu@ybu.edu.cn", "job_title": "教授", "abstracts": null, "directions": null, "education_experience": null, "work_experience": null, "patent": null, "project": null, "award": null, "social_job": null, "picture": "https://nxy.ybu.edu.cn/__local/F/0F/52/E078939CDF517EE46C65F828799_7C5E8A06_8B4C.jpg", "education": "研究生", "qualification": "博士", "job_information": 1, "responsibilities": null, "office_address": null}, {"name": "许钟华", "school_id": 10, "college_id": 87, "phone": "17643301828", "email": "hejonghua@163.com", "job_title": "讲师", "abstracts": null, "directions": null, "education_experience": null, "work_experience": null, "patent": null, "project": null, "award": null, "social_job": null, "picture": "https://nxy.ybu.edu.cn/__local/D/AB/C3/06D787FFA2261B50CF91E1414EE_F4A0D104_27000.jpg", "education": "研究生", "qualification": "博士", "job_information": 1, "responsibilities": null, "office_address": null}, {"name": "贾立军", "school_id": 10, "college_id": 87, "phone": "13844705029", "email": "ljjia@ybu.edu.cn", "job_title": "教授", "abstracts": null, "directions": null, "education_experience": null, "work_experience": null, "patent": null, "project": null, "award": null, "social_job": null, "picture": "https://nxy.ybu.edu.cn/__local/4/21/AC/37B137E0462D67B200D491716CA_ED0953DF_E29E.jpg", "education": "研究生", "qualification": "博士", "job_information": 1, "responsibilities": null, "office_address": null}, {"name": "赵成日", "school_id": 10, "college_id": 87, "phone": "18744333553", "email": "zhaochengri@ybu.edu.cn", "job_title": "讲师", "abstracts": null, "directions": null, "education_experience": null, "work_experience": null, "patent": null, "project": null, "award": null, "social_job": null, "picture": "https://nxy.ybu.edu.cn/__local/1/58/AD/51ED09530A791B16FF3FF35AF40_0A4A218E_657E.jpg", "education": "研究生", "qualification": "博士", "job_information": 1, "responsibilities": null, "office_address": null}, {"name": "赵洪颜", "school_id": 10, "college_id": 87, "phone": "0433-2435568", "email": "zhy@ybu.edu.cn", "job_title": "副教授", "abstracts": null, "directions": null, "education_experience": null, "work_experience": null, "patent": null, "project": null, "award": null, "social_job": null, "picture": "https://nxy.ybu.edu.cn/__local/8/8C/C9/4AB6724E8300CDB74293B0A5106_1F83CEE0_71BE.jpg", "education": "研究生", "qualification": "博士", "job_information": 1, "responsibilities": null, "office_address": null}, {"name": "赵鹏", "school_id": 10, "college_id": 87, "phone": "18804339056", "email": "0000005131@ybu.edu.cn", "job_title": "讲师", "abstracts": null, "directions": null, "education_experience": null, "work_experience": null, "patent": null, "project": null, "award": null, "social_job": null, "picture": "https://nxy.ybu.edu.cn/__local/C/E1/4C/5D887F86F635DB56A9EEF66EBF4_9E5D2B04_4D64.jpg", "education": "研究生", "qualification": "博士", "job_information": 1, "responsibilities": null, "office_address": null}, {"name": "郑大浩", "school_id": 10, "college_id": 87, "phone": "13944741290", "email": "ljzdhdh@163.com", "job_title": "教授", "abstracts": null, "directions": null, "education_experience": null, "work_experience": null, "patent": null, "project": null, "award": null, "social_job": null, "picture": "https://nxy.ybu.edu.cn/__local/8/A2/13/A1E3FC81474AFCF08F1170733D1_402071C5_6929.jpg", "education": "研究生", "qualification": "博士", "job_information": 1, "responsibilities": null, "office_address": null}, {"name": "郭中校", "school_id": 10, "college_id": 87, "phone": "15104310000", "email": "guozhx@cjaas.com", "job_title": "研究员", "abstracts": null, "directions": null, "education_experience": null, "work_experience": null, "patent": null, "project": null, "award": null, "social_job": null, "picture": "https://nxy.ybu.edu.cn/__local/8/FB/BE/2FE6E7DF94E5C9F4C7FCA3A8043_FDB0DB7D_35583.png", "education": "研究生", "qualification": "博士", "job_information": 1, "responsibilities": null, "office_address": null}, {"name": "郭志军", "school_id": 10, "college_id": 87, "phone": "0433-2435549", "email": "guozhijunvip@163.com", "job_title": "副教授", "abstracts": null, "directions": null, "education_experience": null, "work_experience": null, "patent": null, "project": null, "award": null, "social_job": null, "picture": "https://nxy.ybu.edu.cn/__local/7/B2/59/46148CEBFAFAE7C0FDB035673D8_2A7BA8D8_4282.jpg", "education": "研究生", "qualification": "博士", "job_information": 1, "responsibilities": null, "office_address": null}, {"name": "金一", "school_id": 10, "college_id": 87, "phone": "13944388006", "email": "yijin@ybu.edu.cn", "job_title": "教授", "abstracts": null, "directions": null, "education_experience": null, "work_experience": null, "patent": null, "project": null, "award": null, "social_job": null, "picture": "https://nxy.ybu.edu.cn/__local/5/F9/1B/C5B4679F889BE543F12AB8EC2FE_6B67CD02_14D71.jpg", "education": "研究生", "qualification": "博士", "job_information": 1, "responsibilities": null, "office_address": null}, {"name": "金东春", "school_id": 10, "college_id": 87, "phone": "13904439148", "email": "jindongchun@ybu.edu.cn", "job_title": "高级实验师", "abstracts": null, "directions": null, "education_experience": null, "work_experience": null, "patent": null, "project": null, "award": null, "social_job": null, "picture": "https://nxy.ybu.edu.cn/__local/0/8D/B3/9096C9F36833B00D43E9BBE2D1B_C029565A_856F.png", "education": "研究生", "qualification": "博士", "job_information": 1, "responsibilities": null, "office_address": null}, {"name": "金东淳", "school_id": 10, "college_id": 87, "phone": "0433-2435559", "email": "0000002060@ybu.edu.cn", "job_title": "副教授", "abstracts": null, "directions": null, "education_experience": null, "work_experience": null, "patent": null, "project": null, "award": null, "social_job": null, "picture": "https://nxy.ybu.edu.cn/__local/B/A7/45/E1FE449FAEC81CD66BDD0608219_A39D97FA_9F80.jpg", "education": "研究生", "qualification": "博士", "job_information": 1, "responsibilities": null, "office_address": null}, {"name": "金光洙", "school_id": 10, "college_id": 87, "phone": "13944341783", "email": "jinguangzhu@ybu.edu.cn", "job_title": "副教授", "abstracts": null, "directions": null, "education_experience": null, "work_experience": null, "patent": null, "project": null, "award": null, "social_job": null, "picture": "https://nxy.ybu.edu.cn/__local/2/A9/CC/75211392DAD60F681E9B915E2D5_2008F009_674E.jpg", "education": "研究生", "qualification": "博士", "job_information": 1, "responsibilities": null, "office_address": null}, {"name": "金光虎", "school_id": 10, "college_id": 87, "phone": "13644339500", "email": "jinguanghu@ybu.edu.cn", "job_title": "副教授", "abstracts": null, "directions": null, "education_experience": null, "work_experience": null, "patent": null, "project": null, "award": null, "social_job": null, "picture": "https://nxy.ybu.edu.cn/__local/3/03/F6/5875DE931DFE8053BB41288BC10_AF53E76E_2511B.jpg", "education": "研究生", "qualification": "硕士", "job_information": 1, "responsibilities": null, "office_address": null}, {"name": "金卓", "school_id": 10, "college_id": 87, "phone": "13704467610", "email": "jinzhuo0116@ybu.edu.cn", "job_title": "讲师", "abstracts": null, "directions": null, "education_experience": null, "work_experience": null, "patent": null, "project": null, "award": null, "social_job": null, "picture": "https://nxy.ybu.edu.cn/__local/6/70/B1/655F1788CB89BCFD6AEF5AE6DFE_8AC4706A_36773.png", "education": "研究生", "qualification": "博士", "job_information": 1, "responsibilities": null, "office_address": null}, {"name": "金庆国", "school_id": 10, "college_id": 87, "phone": "18204331166", "email": "qgjin@ybu.edu.cn", "job_title": "讲师", "abstracts": null, "directions": null, "education_experience": null, "work_experience": null, "patent": null, "project": null, "award": null, "social_job": null, "picture": "https://nxy.ybu.edu.cn/__local/B/20/E5/D0C1C1D77778DF7AE9305390290_4732AB36_86A1.jpg", "education": "研究生", "qualification": "博士", "job_information": 1, "responsibilities": null, "office_address": null}, {"name": "金明姬", "school_id": 10, "college_id": 87, "phone": "15004337363", "email": "jinmingji@ybu.edu.cn", "job_title": "教授", "abstracts": null, "directions": null, "education_experience": null, "work_experience": null, "patent": null, "project": null, "award": null, "social_job": null, "picture": "https://nxy.ybu.edu.cn/__local/2/68/C1/12A96918ED2FB9E282FD99D6973_4583D550_7A09.png", "education": "研究生", "qualification": "博士", "job_information": 1, "responsibilities": null, "office_address": null}, {"name": "金春梅", "school_id": 10, "college_id": 87, "phone": "13944708032", "email": "0000002029@ybu.edu.cn", "job_title": "讲师", "abstracts": null, "directions": null, "education_experience": null, "work_experience": null, "patent": null, "project": null, "award": null, "social_job": null, "picture": "https://nxy.ybu.edu.cn/__local/9/FC/5A/29DD627058413730DA4F03A96FD_9315ED30_64E8.jpg", "education": "研究生", "qualification": "博士", "job_information": 1, "responsibilities": null, "office_address": null}, {"name": "金江山", "school_id": 10, "college_id": 87, "phone": "0433-2435599", "email": null, "job_title": "副教授", "abstracts": null, "directions": null, "education_experience": null, "work_experience": null, "patent": null, "project": null, "award": null, "social_job": null, "picture": "https://nxy.ybu.edu.cn/__local/7/AD/80/ACCC88C51315A9F7F4AC894F5B8_4F58AA8D_7713.jpg", "education": "研究生", "qualification": "硕士", "job_information": 1, "responsibilities": null, "office_address": null}, {"name": "金清", "school_id": 10, "college_id": 87, "phone": "0433-2435577", "email": "jinqing@ybu.edu.cn", "job_title": "教授", "abstracts": null, "directions": null, "education_experience": null, "work_experience": null, "patent": null, "project": null, "award": null, "social_job": null, "picture": "https://nxy.ybu.edu.cn/__local/6/C9/7B/B10B3E1A828D848585BED4BEA26_DFB5D56C_5CD7.jpg", "education": "研究生", "qualification": "博士", "job_information": 1, "responsibilities": null, "office_address": null}, {"name": "金美玉", "school_id": 10, "college_id": 87, "phone": "0433-2435625", "email": "jinmeiyu@ybu.edu.cn", "job_title": "实验师", "abstracts": null, "directions": null, "education_experience": null, "work_experience": null, "patent": null, "project": null, "award": null, "social_job": null, "picture": "https://nxy.ybu.edu.cn/__local/C/6E/A1/57F0805E3253C0999C6EA104338_F79399AD_5DFE.jpg", "education": "研究生", "qualification": "博士", "job_information": 1, "responsibilities": null, "office_address": null}, {"name": "金艺华", "school_id": 10, "college_id": 87, "phone": "0433-2435554", "email": "jinyh2018@ybu.edu.cn", "job_title": "讲师", "abstracts": null, "directions": null, "education_experience": null, "work_experience": null, "patent": null, "project": null, "award": null, "social_job": null, "picture": "https://nxy.ybu.edu.cn/__local/F/B5/CB/FCBB70A01C20CB91FAB12F06795_6233331B_7083.jpg", "education": "研究生", "qualification": "博士", "job_information": 1, "responsibilities": null, "office_address": null}, {"name": "金花子", "school_id": 10, "college_id": 87, "phone": "15944326839", "email": "hzjin@ybu.edu.cn", "job_title": "副教授", "abstracts": null, "directions": null, "education_experience": null, "work_experience": null, "patent": null, "project": null, "award": null, "social_job": null, "picture": "https://nxy.ybu.edu.cn/__local/9/17/E6/E769D379436E2627A9A30662451_BC08EC7C_62F4.jpg", "education": "研究生", "qualification": "博士", "job_information": 1, "responsibilities": null, "office_address": null}, {"name": "金英海", "school_id": 10, "college_id": 87, "phone": "0433-2435518", "email": "jinyh@byu.edu.cn", "job_title": "副教授", "abstracts": null, "directions": null, "education_experience": null, "work_experience": null, "patent": null, "project": null, "award": null, "social_job": null, "picture": "https://nxy.ybu.edu.cn/__local/C/2F/CC/34984FA624B289EA854E243D39C_CCA859AF_9B8A.png", "education": "研究生", "qualification": "博士", "job_information": 1, "responsibilities": null, "office_address": null}, {"name": "金英花", "school_id": 10, "college_id": 87, "phone": "0433-2435590", "email": "yhuajin@ybu.edu.cn", "job_title": "副教授", "abstracts": null, "directions": null, "education_experience": null, "work_experience": null, "patent": null, "project": null, "award": null, "social_job": null, "picture": "https://nxy.ybu.edu.cn/__local/3/8A/50/6DDD17F95C813B5C3B0C7224699_B3188418_6481.jpg", "education": "研究生", "qualification": "博士", "job_information": 1, "responsibilities": null, "office_address": null}, {"name": "金鑫", "school_id": 10, "college_id": 87, "phone": "13904436318", "email": "Jinxin@ybu.edu.cn", "job_title": "教授", "abstracts": null, "directions": null, "education_experience": null, "work_experience": null, "patent": null, "project": null, "award": null, "social_job": null, "picture": "https://nxy.ybu.edu.cn/__local/B/0D/42/C8EF66A240585356DC544266845_8008E16D_90DD.jpg", "education": "研究生", "qualification": "博士", "job_information": 1, "responsibilities": null, "office_address": null}, {"name": "金铁", "school_id": 10, "college_id": 87, "phone": "13039334687", "email": "jintie@ybu.edu.cn", "job_title": "讲师", "abstracts": null, "directions": null, "education_experience": null, "work_experience": null, "patent": null, "project": null, "award": null, "social_job": null, "picture": "https://nxy.ybu.edu.cn/__local/8/14/EA/CBF7F4E3FCBAB4AC1E0EC0D6B28_2FE2D3A7_AF14.png", "education": "研究生", "qualification": "博士", "job_information": 1, "responsibilities": null, "office_address": null}, {"name": "金铁岩", "school_id": 10, "college_id": 87, "phone": "18104336998", "email": "jintieyan@ybu.edu.cn", "job_title": "副教授", "abstracts": null, "directions": null, "education_experience": null, "work_experience": null, "patent": null, "project": null, "award": null, "social_job": null, "picture": "https://nxy.ybu.edu.cn/__local/9/CF/5B/69FDA2A71E1D541A19A6A093C4D_710AF606_6B54.jpg", "education": "研究生", "qualification": "博士", "job_information": 1, "responsibilities": null, "office_address": null}, {"name": "金锡九", "school_id": 10, "college_id": 87, "phone": null, "email": "jinxj@ybu.edu.cn", "job_title": "副教授", "abstracts": null, "directions": null, "education_experience": null, "work_experience": null, "patent": null, "project": null, "award": null, "social_job": null, "picture": "https://nxy.ybu.edu.cn/__local/2/17/7F/955079B204E9F4A2AB194B379C2_95E6F750_5AF3.jpg", "education": "研究生", "qualification": "博士", "job_information": 1, "responsibilities": null, "office_address": null}, {"name": "金馨梅", "school_id": 10, "college_id": 87, "phone": "13009081221", "email": "siskim1221@ybu.edu.cn", "job_title": "讲师", "abstracts": null, "directions": null, "education_experience": null, "work_experience": null, "patent": null, "project": null, "award": null, "social_job": null, "picture": "https://nxy.ybu.edu.cn/__local/9/5F/65/264FD0084F4DF4E9A3202881B07_30B135FB_1A4AB.jpg", "education": "研究生", "qualification": "博士", "job_information": 1, "responsibilities": null, "office_address": null}, {"name": "陈璇", "school_id": 10, "college_id": 87, "phone": "15204890489", "email": "0000008862@ybu.edu.cn", "job_title": "讲师", "abstracts": null, "directions": null, "education_experience": null, "work_experience": null, "patent": null, "project": null, "award": null, "social_job": null, "picture": "https://nxy.ybu.edu.cn/__local/F/CD/BD/AB2E125376DC62853F8E1EA2FAD_86CADB7B_1B42.jpg", "education": "研究生", "qualification": "博士", "job_information": 1, "responsibilities": null, "office_address": null}, {"name": "高日", "school_id": 10, "college_id": 87, "phone": "0433-2435571", "email": "gaori@ybu.edu.cn", "job_title": "讲师", "abstracts": null, "directions": null, "education_experience": null, "work_experience": null, "patent": null, "project": null, "award": null, "social_job": null, "picture": "https://nxy.ybu.edu.cn/__local/2/D3/1A/9FE0BDD7F87A53361867282A3A1_36B20C63_6A36.jpg", "education": "研究生", "qualification": "博士", "job_information": 1, "responsibilities": null, "office_address": null}, {"name": "高旭", "school_id": 10, "college_id": 87, "phone": "0433-2435609", "email": "gaoxu@ybu.edu.cn", "job_title": "教授", "abstracts": null, "directions": null, "education_experience": null, "work_experience": null, "patent": null, "project": null, "award": null, "social_job": null, "picture": "https://nxy.ybu.edu.cn/__local/2/0B/FF/5186ECF14C3AF2415F67750195E_1056E09C_6B06D.png", "education": "研究生", "qualification": "博士", "job_information": 1, "responsibilities": null, "office_address": null}, {"name": "高松花", "school_id": 10, "college_id": 87, "phone": "15844337720", "email": "gsh2015@ybu.edu.cn", "job_title": "副教授", "abstracts": null, "directions": null, "education_experience": null, "work_experience": null, "patent": null, "project": null, "award": null, "social_job": null, "picture": "https://nxy.ybu.edu.cn/__local/B/58/F7/44E7C43A128EEF0D0006E898E55_0E251EF5_5EAC.jpg", "education": "研究生", "qualification": "博士", "job_information": 1, "responsibilities": null, "office_address": null}, {"name": "高玉福", "school_id": 10, "college_id": 87, "phone": "18343388328", "email": "gaoyufu@ybu.edu.cn", "job_title": "讲师", "abstracts": null, "directions": null, "education_experience": null, "work_experience": null, "patent": null, "project": null, "award": null, "social_job": null, "picture": "https://nxy.ybu.edu.cn/__local/5/92/C1/ABC4D232F083C2858FB96AFBB47_292D5DF8_6C53F.jpg", "education": "研究生", "qualification": "博士", "job_information": 1, "responsibilities": null, "office_address": null}, {"name": "高青山", "school_id": 10, "college_id": 87, "phone": "13944305673", "email": "qsgao@ybu.edu.cn", "job_title": "副教授", "abstracts": null, "directions": null, "education_experience": null, "work_experience": null, "patent": null, "project": null, "award": null, "social_job": null, "picture": "https://nxy.ybu.edu.cn/__local/9/75/8C/31F302CE14E29AC7EEB45B3AE03_6AFABA55_43F4.jpg", "education": "研究生", "qualification": "博士", "job_information": 1, "responsibilities": null, "office_address": null}, {"name": "黄世臣", "school_id": 10, "college_id": 87, "phone": null, "email": "schuang@ybu.edu.cn", "job_title": "副教授", "abstracts": null, "directions": null, "education_experience": null, "work_experience": null, "patent": null, "project": null, "award": null, "social_job": null, "picture": "https://nxy.ybu.edu.cn/__local/1/11/61/9FFB3DBA199FFBCFF69D1EAA039_3D2408F1_8623F.png", "education": "研究生", "qualification": "博士", "job_information": 1, "responsibilities": null, "office_address": null}]